main.py
alt_ctrl_proj-0.0.4.dist-info/licenses/LICENSE
xer_parser/__init__.py
xer_parser/reader.py
xer_parser/write.py
xer_parser/dcma14/__init__.py
xer_parser/dcma14/analysis.py
xer_parser/model/__init__.py
xer_parser/model/accounts.py
xer_parser/model/activitycodes.py
xer_parser/model/activityresources.py
xer_parser/model/acttypes.py
xer_parser/model/calendars.py
xer_parser/model/currencies.py
xer_parser/model/fintmpls.py
xer_parser/model/nonworks.py
xer_parser/model/obss.py
xer_parser/model/pacttypes.py
xer_parser/model/pcatvals.py
xer_parser/model/predecessors.py
xer_parser/model/projcats.py
xer_parser/model/projects.py
xer_parser/model/rcattypes.py
xer_parser/model/rcatvals.py
xer_parser/model/resources.py
xer_parser/model/rolerates.py
xer_parser/model/roles.py
xer_parser/model/rsrccats.py
xer_parser/model/rsrccurves.py
xer_parser/model/rsrcrates.py
xer_parser/model/schedoptions.py
xer_parser/model/taskactvs.py
xer_parser/model/taskprocs.py
xer_parser/model/tasks.py
xer_parser/model/udftypes.py
xer_parser/model/udfvalues.py
xer_parser/model/wbss.py
xer_parser/model/classes/__init__.py
xer_parser/model/classes/account.py
xer_parser/model/classes/activitycode.py
xer_parser/model/classes/acttype.py
xer_parser/model/classes/calendar.py
xer_parser/model/classes/calendar_data.py
xer_parser/model/classes/currency.py
xer_parser/model/classes/data.py
xer_parser/model/classes/fintmpl.py
xer_parser/model/classes/nonwork.py
xer_parser/model/classes/obs.py
xer_parser/model/classes/p6codes.py
xer_parser/model/classes/pcattype.py
xer_parser/model/classes/pcatval.py
xer_parser/model/classes/projcat.py
xer_parser/model/classes/project.py
xer_parser/model/classes/rcattype.py
xer_parser/model/classes/rcatval.py
xer_parser/model/classes/role.py
xer_parser/model/classes/rolerate.py
xer_parser/model/classes/rsrc.py
xer_parser/model/classes/rsrccurv.py
xer_parser/model/classes/rsrcrate.py
xer_parser/model/classes/rsrcrcat.py
xer_parser/model/classes/schedoption.py
xer_parser/model/classes/task.py
alt_ctrl_proj-0.0.4.dist-info/METADATA
alt_ctrl_proj-0.0.4.dist-info/WHEEL
alt_ctrl_proj-0.0.4.dist-info/entry_points.txt
alt_ctrl_proj-0.0.4.dist-info/top_level.txt
alt_ctrl_proj-0.0.4.dist-info/RECORD
