Metadata-Version: 2.4
Name: Alt-Ctrl-Proj
Version: 0.0.4
Summary: An actively maintained fork of PyP6Xer: A Python parser for Primavera XER files.
Author-email: Osama Ata <me@osamata.com>, Hassan Emam <hassan.emam@hotmail.com>
License: GPL-3.0-or-later
Project-URL: Homepage, https://github.com/osama-ata/Alt-Ctrl-Proj
Project-URL: Documentation, https://github.com/osama-ata/Alt-Ctrl-Proj
Project-URL: Source, https://github.com/osama-ata/Alt-Ctrl-Proj
Project-URL: Issues, https://github.com/osama-ata/Alt-Ctrl-Proj/issues
Classifier: Programming Language :: Python :: 3.10
Classifier: Operating System :: OS Independent
Classifier: License :: OSI Approved :: GNU General Public License v3 or later (GPLv3+)
Classifier: Development Status :: 4 - Beta
Classifier: Intended Audience :: Developers
Classifier: Topic :: Software Development :: Libraries :: Python Modules
Requires-Python: >=3.10
License-File: LICENSE
Provides-Extra: test
Requires-Dist: pytest==8.3.5; extra == "test"
Provides-Extra: dev
Requires-Dist: ruff; extra == "dev"
Requires-Dist: pre-commit; extra == "dev"
Provides-Extra: docs
Requires-Dist: sphinx; extra == "docs"
Requires-Dist: sphinx-rtd-theme; extra == "docs"
Requires-Dist: sphinx-autodoc-typehints; extra == "docs"
Requires-Dist: sphinxcontrib-mermaid; extra == "docs"
Dynamic: license-file
